zkit/__init__.py
zkit/_renderer.py
zeekit-1.0.0.0a0.dist-info/LICENSE
zeekit-1.0.0.0a0.dist-info/METADATA
zeekit-1.0.0.0a0.dist-info/WHEEL
zeekit-1.0.0.0a0.dist-info/top_level.txt
zeekit-1.0.0.0a0.dist-info/RECORD
